setup.py
pytuya/__init__.py
pytuya/const.py
pytuya.egg-info/PKG-INFO
pytuya.egg-info/SOURCES.txt
pytuya.egg-info/dependency_links.txt
pytuya.egg-info/requires.txt
pytuya.egg-info/top_level.txt