Metadata-Version: 1.1
Name: pytuya
Version: 7.0.6
Summary: Python interface to ESP8266MOD WiFi smart devices from Shenzhen Xenon
Home-page: https://github.com/clach04/python-tuya
Author: clach04
Author-email: UNKNOWN
License: MIT
Keywords: home automation
Platform: any
Classifier: Development Status :: 4 - Beta
Classifier: Intended Audience :: Developers
Classifier: Topic :: Home Automation
Classifier: License :: OSI Approved :: MIT License
Classifier: Programming Language :: Python
Classifier: Programming Language :: Python :: 2
Classifier: Programming Language :: Python :: 3
Classifier: Programming Language :: Python :: 3.6
Classifier: Topic :: Home Automation
